{
  "performanceData":
  [
    {
      "min": 1,
      "max": 913,
      "quantile90": 52,
      "average": 47,
      "total": 100,
      "statusCodes":{
                      "200": 100
                    },
      "uriByStatusCode":{
                          "200": [
                                  "INPRO15.1: 60+ Day Delinquency - DELQ_60PLUS",
                                  "INPRO13.2: Cumulative Net Charge Off - CUM_LOSS_COVERAGE",
                                  "Insikt Loans LendingClub : Loan term :30,60 : DELQ_30PLUS - Annual",
                                  "INPRO15.1: 60+ Day Delinquency - DELQ_60PLUS_FORECAST",
                                  "INLCM15.2: 60+ Day Delinquency - DELQ_60PLUS",
                                  "INPRO13.1: 30+ Day Delinquency - DELQ_30PLUS_FORECAST",
                                  "INPRO14.2: 60+ Day Delinquency - DELQ_60PLUS_FORECAST",
                                  "INPRO14.1: 60+ Day Delinquency - DELQ_60PLUS_COVERAGE",
                                  "invest/cro/cro.html",
                                  "INLCM15.2: Cumulative Net Charge Off  - CUM_LOSS_FORECAST",
                                  "Insikt Loans Prosper:Loan term :60 : DELQ_30PLUS - Monthly",
                                  "Insikt Loans Prosper: Quarterly: Loan term :30,60 -CUM_LOSS",
                                  "INPRO13.1: Cumulative Net Charge Off - CUM_LOSS_COVERAGE",
                                  "INLCM15.2: 60+ Day Delinquency - DELQ_60PLUS_FORECAST",
                                  "Insikt Loans LendingClub : Loan term :30,60 : DELQ_30PLUS - Quarterly",
                                  "INPRO15.1: Cumulative Net Charge Off - CUM_LOSS_COVERAGE",
                                  "INPRO15.1: 30+ Day Delinquency - DELQ_30PLUS",
                                  "INPRO14.2: 60+ Day Delinquency - DELQ_60PLUS_COVERAGE",
                                  "INPRO13.2: Cumulative Net Charge Off - CUM_LOSS",
                                  "INPRO14.2: Cumulative Net Charge Off - CUM_LOSS_FORECAST",
                                  "Insikt Loans LendingClub : DELQ_30PLUS : Monthly +36,60 +Prosper",
                                  "INLCM15.3: 30+ Day Delinquency -  DELQ_30PLUS",
                                  "Insikt Loans LendingClub : Loan term :36 : DELQ_30PLUS - Monthly",
                                  "Insikt Loans Prosper:Loan term :30,60 : DELQ_30PLUS - Quarterly",
                                  "INPRO13.2: Cumulative Net Charge Off - CUM_LOSS_FORECAST",
                                  "Insikt Loans Prosper: Quarterly: Loan term : 60",
                                  "Insikt Loans LendingClub : Loan term :36 : DELQ_30PLUS - Quarterly",
                                  "Insikt Loans Prosper:Loan term :36 : DELQ_30PLUS - Monthly",
                                  "INPRO14.1: 60+ Day Delinquency - DELQ_60PLUS",
                                  "INPRO14.1: Cumulative Net Charge Off - CUM_LOSS",
                                  "INPRO13.2: 30+ Day Delinquency - DELQ_30PLUS_COVERAGE",
                                  "INPRO13.2: 60+ Day Delinquency - DELQ_60PLUS_FORECAST",
                                  "Insikt Loans LendingClub: Monthly: Loan term :30,60- DELQ_30PLUS",
                                  "front-page",
                                  "INLCP15.3: Cumulative Net Charge Off - CUM_LOSS_COVERAGE",
                                  "INPRO13.1: 60+ Day Delinquency - DELQ_60PLUS_COVERAGE",
                                  "INPRO15.1: Cumulative Net Charge Off - CUM_LOSS_FORECAST",
                                  "INPRO14.2: 30+ Day Delinquency - DELQ_30PLUS",
                                  "INPRO13.2: 30+ Day Delinquency - DELQ_30PLUS",
                                  "INPRO13.2: 30+ Day Delinquency - DELQ_30PLUS_FORECAST",
                                  "Insikt Loans Prosper: DELQ_30PLUS : Monthly +36,60 +Prosper",
                                  "Insikt Loans Prosper:Loan term :30,60 : DELQ_30PLUS - Monthly",
                                  "Insikt Loans Prosper:Loan term :36 : DELQ_30PLUS - Quarterly",
                                  "Insikt Loans LendingClub : Loan term :36 : DELQ_30PLUS - Annual",
                                  "INPRO13.1: 30+ Day Delinquency - DELQ_30PLUS_COVERAGE",
                                  "INPRO13.2: 60+ Day Delinquency - DELQ_60PLUS_COVERAGE",
                                  "INLCM15.3: 60+ Day Delinquency -  DELQ_60PLUS",
                                  "INLCP15.3: Cumulative Net Charge Off - CUM_LOSS",
                                  "invest/index.html",
                                  "Insikt Loans LendingClub : Loan term :60 : DELQ_30PLUS - Annual",
                                  "INPRO14.1: 30+ Day Delinquency - DELQ_30PLUS",
                                  "INLCM15.2: 30+ Day Delinquency - DELQ_30PLUS_COVERAGE",
                                  "INPRO14.2: 30+ Day Delinquency - DELQ_30PLUS_COVERAGE",
                                  "Insikt Loans LendingClub : Loan term :30,60 : DELQ_30PLUS - Monthly",
                                  "INLCM15.3: 60+ Day Delinquency -  DELQ_60PLUS_FORECAST",
                                  "INPRO14.2: Cumulative Net Charge Off - CUM_LOSS",
                                  "INPRO13.1: 60+ Day Delinquency - DELQ_60PLUS",
                                  "Insikt Loans Prosper:Loan term :36 : DELQ_30PLUS - Annual",
                                  "Insikt Loans Prosper: Quarterly: Loan term : 36",
                                  "Insikt Loans LendingClub: Annual: Loan term :30,60 - DELQ_30PLUS",
                                  "Insikt Loans LendingClub : DELQ_30PLUS : Monthly +60 +Prosper",
                                  "INPRO14.2: Cumulative Net Charge Off - CUM_LOSS_COVERAGE",
                                  "Insikt Loans Prosper:Loan term :60 : DELQ_30PLUS - Quarterly",
                                  "INPRO14.1: Cumulative Net Charge Off - CUM_LOSS_FORECAST",
                                  "INLCM15.3: 30+ Day Delinquency - DELQ_30PLUS_COVERAGE",
                                  "INPRO15.1: 30+ Day Delinquency - DELQ_30PLUS_FORECAST",
                                  "INLCM15.2: Cumulative Net Charge Off  - CUM_LOSS",
                                  "Insikt Loans LendingClub: Quarterly: Loan term :30,60 -CUM_LOSS",
                                  "INPRO13.1: 60+ Day Delinquency - DELQ_60PLUS_FORECAST",
                                  "INPRO14.2: 30+ Day Delinquency - DELQ_30PLUS_FORECAST",
                                  "INPRO14.1: 30+ Day Delinquency - DELQ_30PLUS_COVERAGE",
                                  "Insikt Loans Prosper: DELQ_30PLUS : Monthly +60 +Prosper",
                                  "INLCP15.3: Cumulative Net Charge Off - CUM_LOSS_FORECAST",
                                  "mycro configuration",
                                  "INPRO15.1: Cumulative Net Charge Off - CUM_LOSS",
                                  "Insikt Loans LendingClub : Loan term :60 : DELQ_30PLUS - Quarterly",
                                  "INLCM15.3: 60+ Day Delinquency -  DELQ_60PLUS_COVERAGE",
                                  "Insikt Loans Prosper: Annual: Loan term :30,60 -DELQ_30PLUS",
                                  "INPRO13.1: Cumulative Net Charge Off - CUM_LOSS_FORECAST",
                                  "INLCM15.3: 30+ Day Delinquency - DELQ_30PLUS_FORECAST",
                                  "Insikt Loans Prosper:Loan term :60 : DELQ_30PLUS - Annual",
                                  "INPRO15.1: 60+ Day Delinquency - DELQ_60PLUS_COVERAGE",
                                  "INLCM15.2: 30+ Day Delinquency - DELQ_30PLUS",
                                  "INLCM15.2: 30+ Day Delinquency - DELQ_30PLUS_FORECAST",
                                  "INLCM15.2: Cumulative Net Charge Off  - CUM_LOSS_COVERAGE",
                                  "INPRO13.1: 30+ Day Delinquency - DELQ_30PLUS",
                                  "Insikt Loans LendingClub: 30+ Day Delinquency: Loan term :30,60",
                                  "INPRO14.1: Cumulative Net Charge Off - CUM_LOSS_COVERAGE",
                                  "Insikt Loans Prosper: 30+ Day Delinquency: Loan term :30,60 - CUM_LOSS",
                                  "INPRO14.1: 30+ Day Delinquency - DELQ_30PLUS_FORECAST",
                                  "INLCM15.2: 60+ Day Delinquency - DELQ_60PLUS_COVERAGE",
                                  "INPRO15.1: 30+ Day Delinquency - DELQ_30PLUS_COVERAGE",
                                  "Debug Sampler",
                                  "INPRO14.1: 60+ Day Delinquency - DELQ_60PLUS_FORECAST",
                                  "INPRO14.2: 60+ Day Delinquency - DELQ_60PLUS",
                                  "Insikt Loans LendingClub : Loan term :60 : DELQ_30PLUS - Monthly",
                                  "Insikt Loans Prosper:Loan term :30,60 : DELQ_30PLUS - Annual",
                                  "INPRO13.1: Cumulative Net Charge Off - CUM_LOSS",
                                  "INPRO13.2: 60+ Day Delinquency - DELQ_60PLUS",
                                  "Insikt Loans Prosper: Monthly: Loan term :30,60 -DELQ_30PLUS"
                                 ]
                        }
    }
  ]
}